{"name":"shuilongjuan","imagePath":"shuilongjuan_tex.png","SubTexture":[{"width":162,"y":1,"height":88,"name":"Special12_01","x":681},{"width":168,"y":1,"height":149,"name":"Special12_03","x":511},{"width":168,"y":1,"height":151,"name":"Special12_05","x":341},{"width":168,"y":154,"height":151,"name":"Special12_07","x":171},{"width":168,"y":1,"height":151,"name":"Special12_09","x":171},{"width":168,"y":154,"height":151,"name":"Special12_11","x":341},{"width":168,"y":307,"height":151,"name":"Special12_13","x":171},{"width":168,"y":307,"height":150,"name":"Special12_15","x":341},{"width":168,"y":172,"height":166,"name":"Special12_17","x":1},{"width":168,"y":340,"height":162,"name":"Special12_19","x":1},{"width":168,"y":1,"height":169,"name":"Special12_21","x":1}]}