{"armature":[{"bone":[{"transform":{},"name":"root"},{"length":62,"transform":{"y":-37.25,"skX":-88.7546,"skY":-88.7546,"x":9.5302},"parent":"root","name":"bone"}],"animation":[{"bone":[{"frame":[{"tweenEasing":null,"duration":25,"transform":{}}],"name":"root"},{"frame":[{"tweenEasing":0,"duration":2,"transform":{}},{"tweenEasing":0,"duration":1,"transform":{}},{"tweenEasing":0,"duration":1,"transform":{}},{"tweenEasing":0,"duration":1,"transform":{}},{"tweenEasing":0,"duration":2,"transform":{}},{"tweenEasing":0,"duration":1,"transform":{}},{"tweenEasing":0,"duration":1,"transform":{}},{"tweenEasing":0,"duration":1,"transform":{}},{"tweenEasing":0,"duration":2,"transform":{}},{"tweenEasing":0,"duration":1,"transform":{}},{"tweenEasing":0,"duration":1,"transform":{}},{"tweenEasing":0,"duration":1,"transform":{}},{"tweenEasing":0,"duration":2,"transform":{}},{"tweenEasing":0,"duration":1,"transform":{}},{"tweenEasing":0,"duration":1,"transform":{}},{"tweenEasing":0,"duration":1,"transform":{}},{"tweenEasing":0,"duration":2,"transform":{}},{"tweenEasing":0,"duration":1,"transform":{}},{"tweenEasing":0,"duration":1,"transform":{}},{"tweenEasing":0,"duration":1,"transform":{}},{"tweenEasing":null,"duration":0,"transform":{}}],"name":"bone"}],"frame":[],"playTimes":0,"duration":25,"ffd":[],"name":"newAnimation","slot":[{"frame":[{"tweenEasing":null,"duration":2},{"displayIndex":-1,"tweenEasing":null,"duration":23}],"name":"NO-0001"},{"frame":[{"displayIndex":-1,"tweenEasing":null,"duration":2},{"tweenEasing":0,"duration":1},{"displayIndex":-1,"tweenEasing":null,"duration":22}],"name":"NO-0002"},{"frame":[{"displayIndex":-1,"tweenEasing":null,"duration":3},{"tweenEasing":0,"duration":1},{"displayIndex":-1,"tweenEasing":null,"duration":21}],"name":"NO-0003"},{"frame":[{"displayIndex":-1,"tweenEasing":null,"duration":4},{"tweenEasing":0,"duration":1},{"displayIndex":-1,"tweenEasing":null,"duration":20}],"name":"NO-0004"},{"frame":[{"displayIndex":-1,"tweenEasing":null,"duration":5},{"tweenEasing":0,"duration":2},{"displayIndex":-1,"tweenEasing":null,"duration":18}],"name":"NO-0005"},{"frame":[{"displayIndex":-1,"tweenEasing":null,"duration":7},{"tweenEasing":0,"duration":1},{"displayIndex":-1,"tweenEasing":null,"duration":17}],"name":"NO-0006"},{"frame":[{"displayIndex":-1,"tweenEasing":null,"duration":8},{"tweenEasing":0,"duration":1},{"displayIndex":-1,"tweenEasing":null,"duration":16}],"name":"NO-0007"},{"frame":[{"displayIndex":-1,"tweenEasing":null,"duration":9},{"tweenEasing":0,"duration":1},{"displayIndex":-1,"tweenEasing":null,"duration":15}],"name":"NO-0008"},{"frame":[{"displayIndex":-1,"tweenEasing":null,"duration":10},{"tweenEasing":0,"duration":2},{"displayIndex":-1,"tweenEasing":null,"duration":13}],"name":"NO-0009"},{"frame":[{"displayIndex":-1,"tweenEasing":null,"duration":12},{"tweenEasing":0,"duration":1},{"displayIndex":-1,"tweenEasing":null,"duration":12}],"name":"NO-0010"},{"frame":[{"displayIndex":-1,"tweenEasing":null,"duration":13},{"tweenEasing":0,"duration":1},{"displayIndex":-1,"tweenEasing":null,"duration":11}],"name":"NO-0011"},{"frame":[{"displayIndex":-1,"tweenEasing":null,"duration":14},{"tweenEasing":0,"duration":1},{"displayIndex":-1,"tweenEasing":null,"duration":10}],"name":"NO-0012"},{"frame":[{"displayIndex":-1,"tweenEasing":null,"duration":15},{"tweenEasing":0,"duration":2},{"displayIndex":-1,"tweenEasing":null,"duration":8}],"name":"NO-0013"},{"frame":[{"displayIndex":-1,"tweenEasing":null,"duration":17},{"tweenEasing":0,"duration":1},{"displayIndex":-1,"tweenEasing":null,"duration":7}],"name":"NO-0014"},{"frame":[{"displayIndex":-1,"tweenEasing":null,"duration":18},{"tweenEasing":0,"duration":1},{"displayIndex":-1,"tweenEasing":null,"duration":6}],"name":"NO-0015"},{"frame":[{"displayIndex":-1,"tweenEasing":null,"duration":19},{"tweenEasing":0,"duration":1},{"displayIndex":-1,"tweenEasing":null,"duration":5}],"name":"NO-0016"},{"frame":[{"displayIndex":-1,"tweenEasing":null,"duration":20},{"tweenEasing":0,"duration":2},{"displayIndex":-1,"tweenEasing":null,"duration":3}],"name":"NO-0017"},{"frame":[{"displayIndex":-1,"tweenEasing":null,"duration":22},{"tweenEasing":0,"duration":1},{"displayIndex":-1,"tweenEasing":null,"duration":2}],"name":"NO-0018"},{"frame":[{"displayIndex":-1,"tweenEasing":null,"duration":23},{"tweenEasing":0,"duration":1},{"displayIndex":-1,"tweenEasing":null,"duration":1}],"name":"NO-0019"},{"frame":[{"displayIndex":-1,"tweenEasing":null,"duration":24},{"tweenEasing":0,"duration":1},{"displayIndex":-1,"tweenEasing":null,"duration":0}],"name":"NO-0020"}]}],"type":"Armature","name":"sajinbi","aabb":{"width":14,"y":-32.607454261253224,"height":28,"x":8.364956614135707},"slot":[{"name":"NO-0001","parent":"bone","color":{}},{"displayIndex":-1,"z":1,"name":"NO-0002","parent":"bone","color":{}},{"displayIndex":-1,"z":2,"name":"NO-0003","parent":"bone","color":{}},{"displayIndex":-1,"z":3,"name":"NO-0004","parent":"bone","color":{}},{"displayIndex":-1,"z":4,"name":"NO-0005","parent":"bone","color":{}},{"displayIndex":-1,"z":5,"name":"NO-0006","parent":"bone","color":{}},{"displayIndex":-1,"z":6,"name":"NO-0007","parent":"bone","color":{}},{"displayIndex":-1,"z":7,"name":"NO-0008","parent":"bone","color":{}},{"displayIndex":-1,"z":8,"name":"NO-0009","parent":"bone","color":{}},{"displayIndex":-1,"z":9,"name":"NO-0010","parent":"bone","color":{}},{"displayIndex":-1,"z":10,"name":"NO-0011","parent":"bone","color":{}},{"displayIndex":-1,"z":11,"name":"NO-0012","parent":"bone","color":{}},{"displayIndex":-1,"z":12,"name":"NO-0013","parent":"bone","color":{}},{"displayIndex":-1,"z":13,"name":"NO-0014","parent":"bone","color":{}},{"displayIndex":-1,"z":14,"name":"NO-0015","parent":"bone","color":{}},{"displayIndex":-1,"z":15,"name":"NO-0016","parent":"bone","color":{}},{"displayIndex":-1,"z":16,"name":"NO-0017","parent":"bone","color":{}},{"displayIndex":-1,"z":17,"name":"NO-0018","parent":"bone","color":{}},{"displayIndex":-1,"z":18,"name":"NO-0019","parent":"bone","color":{}},{"displayIndex":-1,"z":19,"name":"NO-0020","parent":"bone","color":{}}],"ik":[],"skin":[{"name":"","slot":[{"display":[{"type":"image","name":"NO-0012","transform":{"y":-4.998,"skX":88.7546,"skY":88.7546,"x":84.2687}}],"name":"NO-0012"},{"display":[{"type":"image","name":"NO-0017","transform":{"y":-28.1881,"skX":88.7546,"skY":88.7546,"x":92.7667}}],"name":"NO-0017"},{"display":[{"type":"image","name":"NO-0005","transform":{"y":-0.7164,"skX":88.7546,"skY":88.7546,"x":25.3479}}],"name":"NO-0005"},{"display":[{"type":"image","name":"NO-0003","transform":{"y":4.8258,"skX":88.7546,"skY":88.7546,"x":0.4624}}],"name":"NO-0003"},{"display":[{"type":"image","name":"NO-0020","transform":{"y":43.0342,"skX":88.7546,"skY":88.7546,"x":129.3233}}],"name":"NO-0020"},{"display":[{"type":"image","name":"NO-0001","transform":{"y":6.2385,"skX":88.7546,"skY":88.7546,"x":-18.5113}}],"name":"NO-0001"},{"display":[{"type":"image","name":"NO-0008","transform":{"y":-2.5855,"skX":88.7546,"skY":88.7546,"x":65.3167}}],"name":"NO-0008"},{"display":[{"type":"image","name":"NO-0013","transform":{"y":-5.0414,"skX":88.7546,"skY":88.7546,"x":86.2683}}],"name":"NO-0013"},{"display":[{"type":"image","name":"NO-0018","transform":{"y":-29.2096,"skX":88.7546,"skY":88.7546,"x":93.7448}}],"name":"NO-0018"},{"display":[{"type":"image","name":"NO-0015","transform":{"y":-5.1066,"skX":88.7546,"skY":88.7546,"x":89.2676}}],"name":"NO-0015"},{"display":[{"type":"image","name":"NO-0006","transform":{"y":-0.1295,"skX":88.7546,"skY":88.7546,"x":44.3651}}],"name":"NO-0006"},{"display":[{"type":"image","name":"NO-0011","transform":{"y":-2.9332,"skX":88.7546,"skY":88.7546,"x":81.3129}}],"name":"NO-0011"},{"display":[{"type":"image","name":"NO-0016","transform":{"y":-5.1718,"skX":88.7546,"skY":88.7546,"x":92.2668}}],"name":"NO-0016"},{"display":[{"type":"image","name":"NO-0004","transform":{"y":1.4353,"skX":88.7546,"skY":88.7546,"x":18.393}}],"name":"NO-0004"},{"display":[{"type":"image","name":"NO-0010","transform":{"y":-0.8468,"skX":88.7546,"skY":88.7546,"x":77.3573}}],"name":"NO-0010"},{"display":[{"type":"image","name":"NO-0009","transform":{"y":-4.7806,"skX":88.7546,"skY":88.7546,"x":74.2711}}],"name":"NO-0009"},{"display":[{"type":"image","name":"NO-0014","transform":{"y":-6.0847,"skX":88.7546,"skY":88.7546,"x":88.2461}}],"name":"NO-0014"},{"display":[{"type":"image","name":"NO-0019","transform":{"y":38.0354,"skX":88.7546,"skY":88.7546,"x":129.2146}}],"name":"NO-0019"},{"display":[{"type":"image","name":"NO-0002","transform":{"y":6.7384,"skX":88.7546,"skY":88.7546,"x":4.505}}],"name":"NO-0002"},{"display":[{"type":"image","name":"NO-0007","transform":{"y":-3.4114,"skX":88.7546,"skY":88.7546,"x":57.2968}}],"name":"NO-0007"}]}],"frameRate":24,"defaultActions":[{"gotoAndPlay":"newAnimation"}]}],"frameRate":24,"isGlobal":0,"name":"sajinbi","version":"5.0"}