{"width":256,"SubTexture":[{"width":141,"y":1,"height":65,"name":"1_副本","x":1},{"width":27,"y":141,"height":36,"name":"26","x":74},{"width":27,"y":200,"height":34,"name":"25","x":53},{"width":24,"y":68,"height":35,"name":"24","x":118},{"width":34,"y":122,"height":35,"name":"23","x":126},{"width":46,"y":54,"height":66,"name":"22","x":207},{"width":33,"y":114,"height":44,"name":"21","x":1},{"width":45,"y":108,"height":31,"name":"20","x":79},{"width":22,"y":236,"height":17,"name":"19","x":53},{"width":81,"y":1,"height":51,"name":"18","x":144},{"width":20,"y":202,"height":38,"name":"17","x":1},{"width":37,"y":68,"height":38,"name":"16","x":79},{"width":26,"y":1,"height":42,"name":"15","x":227},{"width":26,"y":161,"height":37,"name":"14","x":28},{"width":20,"y":179,"height":10,"name":"13","x":82},{"width":16,"y":161,"height":8,"name":"12","x":56},{"width":14,"y":105,"height":14,"name":"11","x":126},{"width":24,"y":179,"height":17,"name":"10","x":56},{"width":33,"y":68,"height":52,"name":"9","x":44},{"width":25,"y":160,"height":40,"name":"8","x":1},{"width":61,"y":54,"height":66,"name":"7","x":144},{"width":34,"y":242,"height":13,"name":"6","x":1},{"width":34,"y":242,"height":9,"name":"5","x":77},{"width":36,"y":122,"height":37,"name":"4","x":36},{"width":12,"y":141,"height":21,"name":"3","x":103},{"width":23,"y":200,"height":40,"name":"2","x":28},{"width":41,"y":68,"height":44,"name":"1","x":1}],"imagePath":"yejl_tex.png","name":"yejl","height":256}