{"imagePath":"zhendizhiwang_tex.png","width":1024,"height":2048,"name":"zhendizhiwang","SubTexture":[{"frameWidth":394,"y":1256,"frameHeight":284,"frameY":-36,"width":240,"frameX":-75,"height":218,"name":"bz2_06","x":545},{"frameWidth":364,"y":1707,"frameHeight":262,"frameY":-19,"width":262,"frameX":-32,"height":226,"name":"bz2_03","x":1},{"frameWidth":382,"y":411,"frameHeight":276,"frameY":-25,"width":289,"frameX":-25,"height":230,"name":"bz2_04","x":734},{"frameWidth":384,"y":1494,"frameHeight":274,"frameY":-44,"width":228,"frameX":-75,"height":193,"name":"bz2_07","x":264},{"frameWidth":193,"y":233,"frameHeight":158,"frameY":-10,"width":186,"frameX":-3,"height":139,"name":"bz2_01","x":736},{"frameWidth":334,"y":817,"frameHeight":238,"frameY":-8,"width":308,"frameX":-13,"height":222,"name":"bz2_02","x":699},{"frameWidth":406,"y":1249,"frameHeight":292,"frameY":-26,"width":256,"frameX":-74,"height":243,"name":"bz2_05","x":287},{"frameWidth":512,"y":820,"frameHeight":512,"frameY":-151,"width":341,"frameX":-80,"height":201,"name":"bz_02","x":1},{"frameWidth":512,"y":411,"frameHeight":512,"frameY":-151,"width":363,"frameX":-76,"height":201,"name":"bz_05","x":369},{"frameWidth":512,"y":206,"frameHeight":512,"frameY":-151,"width":367,"frameX":-79,"height":201,"name":"bz_07","x":1},{"frameWidth":512,"y":1,"frameHeight":512,"frameY":-151,"width":368,"frameX":-78,"height":202,"name":"bz_06","x":372},{"frameWidth":512,"y":817,"frameHeight":512,"frameY":-151,"width":347,"frameX":-83,"height":201,"name":"bz_01","x":350},{"frameWidth":512,"y":1,"frameHeight":512,"frameY":-150,"width":369,"frameX":-74,"height":203,"name":"bz_08","x":1},{"frameWidth":512,"y":614,"frameHeight":512,"frameY":-151,"width":354,"frameX":-88,"height":201,"name":"bz_03","x":350},{"frameWidth":512,"y":205,"frameHeight":512,"frameY":-148,"width":362,"frameX":-76,"height":204,"name":"bz_09","x":372},{"frameWidth":512,"y":409,"frameHeight":512,"frameY":-151,"width":366,"frameX":-73,"height":201,"name":"bz_04","x":1},{"frameWidth":512,"y":612,"frameHeight":512,"frameY":-146,"width":347,"frameX":-75,"height":206,"name":"bz_10","x":1},{"frameWidth":325,"y":1020,"frameHeight":234,"frameY":-4,"width":294,"frameX":-25,"height":227,"name":"sf_04","x":344},{"frameWidth":325,"y":1,"frameHeight":234,"frameY":-2,"width":272,"frameX":-29,"height":230,"name":"sf_06","x":742},{"frameWidth":325,"y":1041,"frameHeight":234,"frameY":-10,"width":293,"frameX":-2,"height":213,"name":"sf_01","x":640},{"frameWidth":325,"y":1023,"frameHeight":234,"frameY":-5,"width":284,"frameX":-30,"height":225,"name":"sf_05","x":1},{"frameWidth":325,"y":1477,"frameHeight":234,"frameY":-6,"width":261,"frameX":-22,"height":228,"name":"sf_03","x":1},{"frameWidth":325,"y":1250,"frameHeight":234,"frameY":-6,"width":274,"frameX":-21,"height":225,"name":"sf_02","x":1}]}