{"width":256,"height":256,"name":"shenqibg","imagePath":"shenqibg_tex.png","SubTexture":[{"y":61,"frameY":0,"frameWidth":115,"width":97,"frameX":-9,"frameHeight":58,"height":58,"name":"eft_light01_03","x":1},{"y":121,"frameY":0,"frameWidth":115,"width":97,"frameX":-9,"frameHeight":58,"height":58,"name":"eft_light01_06","x":100},{"y":1,"frameY":0,"frameWidth":115,"width":97,"frameX":-9,"frameHeight":58,"height":58,"name":"eft_light01_07","x":1},{"y":61,"frameY":0,"frameWidth":115,"width":97,"frameX":-9,"frameHeight":58,"height":58,"name":"eft_light01_04","x":100},{"y":181,"frameY":0,"frameWidth":115,"width":97,"frameX":-9,"frameHeight":58,"height":58,"name":"eft_light01_01","x":100},{"y":1,"frameY":0,"frameWidth":115,"width":97,"frameX":-9,"frameHeight":58,"height":58,"name":"eft_light01_08","x":100},{"y":181,"frameY":0,"frameWidth":115,"width":97,"frameX":-9,"frameHeight":58,"height":58,"name":"eft_light01_05","x":1},{"y":121,"frameY":0,"frameWidth":115,"width":97,"frameX":-9,"frameHeight":58,"height":58,"name":"eft_light01_02","x":1}]}