{"width":128,"height":256,"name":"eft_starflash01","imagePath":"eft_starflash01_tex.png","SubTexture":[{"y":201,"frameY":-78,"frameWidth":144,"width":39,"frameX":-84,"frameHeight":139,"height":30,"name":"星光闪闪0012","x":44},{"y":1,"frameY":-75,"frameWidth":144,"width":59,"frameX":-80,"frameHeight":139,"height":56,"name":"星光闪闪0003","x":61},{"y":164,"frameY":-88,"frameWidth":144,"width":40,"frameX":-76,"frameHeight":139,"height":35,"name":"星光闪闪0009","x":44},{"y":1,"frameY":-82,"frameWidth":144,"width":58,"frameX":-86,"frameHeight":139,"height":57,"name":"星光闪闪0004","x":1},{"y":60,"frameY":-77,"frameWidth":144,"width":46,"frameX":-86,"frameHeight":139,"height":51,"name":"星光闪闪0006","x":1},{"y":117,"frameY":-69,"frameWidth":144,"width":49,"frameX":-77,"frameHeight":139,"height":45,"name":"星光闪闪0001","x":49},{"y":163,"frameY":-83,"frameWidth":144,"width":41,"frameX":-79,"frameHeight":139,"height":35,"name":"星光闪闪0010","x":1},{"y":204,"frameY":-87,"frameWidth":144,"width":34,"frameX":-81,"frameHeight":139,"height":32,"name":"星光闪闪0008","x":85},{"y":164,"frameY":-77,"frameWidth":144,"width":36,"frameX":-85,"frameHeight":139,"height":38,"name":"星光闪闪0007","x":86},{"y":113,"frameY":-84,"frameWidth":144,"width":46,"frameX":-92,"frameHeight":139,"height":48,"name":"星光闪闪0005","x":1},{"y":200,"frameY":-76,"frameWidth":144,"width":41,"frameX":-84,"frameHeight":139,"height":35,"name":"星光闪闪0011","x":1},{"y":59,"frameY":-65,"frameWidth":144,"width":58,"frameX":-73,"frameHeight":139,"height":56,"name":"星光闪闪0002","x":61}]}